kedro_mlflow/__init__.py
kedro_mlflow/config/__init__.py
kedro_mlflow/config/kedro_mlflow_config.py
kedro_mlflow/config/resolvers.py
kedro_mlflow/framework/__init__.py
kedro_mlflow/framework/cli/__init__.py
kedro_mlflow/framework/cli/cli.py
kedro_mlflow/framework/cli/cli_utils.py
kedro_mlflow/framework/hooks/__init__.py
kedro_mlflow/framework/hooks/mlflow_hook.py
kedro_mlflow/framework/hooks/utils.py
kedro_mlflow/io/__init__.py
kedro_mlflow/io/artifacts/__init__.py
kedro_mlflow/io/artifacts/mlflow_artifact_dataset.py
kedro_mlflow/io/catalog/__init__.py
kedro_mlflow/io/catalog/switch_catalog_logging.py
kedro_mlflow/io/metrics/__init__.py
kedro_mlflow/io/metrics/mlflow_abstract_metric_dataset.py
kedro_mlflow/io/metrics/mlflow_metric_dataset.py
kedro_mlflow/io/metrics/mlflow_metric_history_dataset.py
kedro_mlflow/io/metrics/mlflow_metrics_history_dataset.py
kedro_mlflow/io/models/__init__.py
kedro_mlflow/io/models/mlflow_abstract_model_dataset.py
kedro_mlflow/io/models/mlflow_model_local_filesystem_dataset.py
kedro_mlflow/io/models/mlflow_model_registry_dataset.py
kedro_mlflow/io/models/mlflow_model_tracking_dataset.py
kedro_mlflow/mlflow/__init__.py
kedro_mlflow/mlflow/kedro_pipeline_model.py
kedro_mlflow/pipeline/__init__.py
kedro_mlflow/pipeline/pipeline_ml.py
kedro_mlflow/pipeline/pipeline_ml_factory.py
kedro_mlflow/template/project/mlflow.yml
kedro_mlflow-1.0.2.dist-info/licenses/LICENSE
kedro_mlflow-1.0.2.dist-info/METADATA
kedro_mlflow-1.0.2.dist-info/WHEEL
kedro_mlflow-1.0.2.dist-info/entry_points.txt
kedro_mlflow-1.0.2.dist-info/top_level.txt
kedro_mlflow-1.0.2.dist-info/RECORD
