Metadata-Version: 2.4
Name: kedro_mlflow
Version: 1.0.2
Summary: A kedro-plugin to use mlflow in your kedro projects
Author: Yolan Honoré-Rougé
License: Apache Software License (Apache 2.0)
Project-URL: Source, https://github.com/Galileo-Galilei/kedro-mlflow
Project-URL: Documentation, https://kedro-mlflow.readthedocs.io/en/stable/
Project-URL: Tracker, https://github.com/Galileo-Galilei/kedro-mlflow/issues
Keywords: kedro-plugin,kedro,mlflow,experiment tracking,model versioning,model serving,machine learning,data pipelines,data science,ml engineering,mlops
Classifier: Development Status :: 4 - Beta
Classifier: Programming Language :: Python :: 3.10
Classifier: Programming Language :: Python :: 3.11
Classifier: Programming Language :: Python :: 3.12
Classifier: Programming Language :: Python :: 3.13
Classifier: Framework :: Kedro
Classifier: Environment :: Plugins
Classifier: Intended Audience :: Developers
Classifier: Operating System :: Microsoft :: Windows
Classifier: Operating System :: MacOS
Classifier: Operating System :: POSIX :: Linux
Requires-Python: >=3.10
License-File: LICENSE
Requires-Dist: kedro<2.0.0,>=1.0.0
Requires-Dist: mlflow<3.0.0,>=2.7.0
Requires-Dist: pydantic<3.0.0,>=1.0.0
Provides-Extra: test
Requires-Dist: pytest<9.0.0,>=5.4.0; extra == "test"
Requires-Dist: pytest-cov<7.0.0,>=2.8.0; extra == "test"
Requires-Dist: pytest-lazy-fixtures<2.0.0,>=1.0.0; extra == "test"
Requires-Dist: pytest-mock<4.0.0,>=3.1.0; extra == "test"
Requires-Dist: pytest-xdist<4.0.0,>=3.0.0; extra == "test"
Requires-Dist: ruff<1.0.0,>=0.5.0; extra == "test"
Requires-Dist: scikit-learn<1.7.0,>=0.23.0; extra == "test"
Requires-Dist: kedro-datasets[pandas.CSVDataSet]>=8.0.0; extra == "test"
Provides-Extra: doc
Requires-Dist: sphinx<9.0.0,>=4.5.0; extra == "doc"
Requires-Dist: sphinx-markdown-tables~=0.0.15; extra == "doc"
Requires-Dist: sphinx-click<6.1,>=3.1; extra == "doc"
Requires-Dist: sphinx_copybutton~=0.5.0; extra == "doc"
Requires-Dist: myst-parser<4.1.0,>=0.17.2; extra == "doc"
Requires-Dist: sphinx_design<0.7.0,>=0.6.0; extra == "doc"
Requires-Dist: pydata-sphinx-theme<0.17.0,>=0.16.0; extra == "doc"
Provides-Extra: dev
Requires-Dist: pre-commit<5.0.0,>=2.0.0; extra == "dev"
Requires-Dist: ipykernel; extra == "dev"
Provides-Extra: all
Requires-Dist: kedro_mlflow[dev,doc,test]; extra == "all"
Dynamic: license-file
